pymodaq_plugins_nkt/__init__.py
pymodaq_plugins_nkt/utils.py
pymodaq_plugins_nkt/app/__init__.py
pymodaq_plugins_nkt/app/custom_app_template.py
pymodaq_plugins_nkt/daq_move_plugins/__init__.py
pymodaq_plugins_nkt/daq_move_plugins/daq_move_SuperK_Extreme.py
pymodaq_plugins_nkt/daq_viewer_plugins/__init__.py
pymodaq_plugins_nkt/daq_viewer_plugins/plugins_0D/__init__.py
pymodaq_plugins_nkt/daq_viewer_plugins/plugins_0D/daq_0Dviewer_Template.py
pymodaq_plugins_nkt/daq_viewer_plugins/plugins_1D/__init__.py
pymodaq_plugins_nkt/daq_viewer_plugins/plugins_1D/daq_1Dviewer_Template.py
pymodaq_plugins_nkt/daq_viewer_plugins/plugins_2D/__init__.py
pymodaq_plugins_nkt/daq_viewer_plugins/plugins_2D/daq_2Dviewer_Template.py
pymodaq_plugins_nkt/daq_viewer_plugins/plugins_ND/__init__.py
pymodaq_plugins_nkt/exporters/__init__.py
pymodaq_plugins_nkt/extensions/__init__.py
pymodaq_plugins_nkt/extensions/custom_extension_template.py
pymodaq_plugins_nkt/hardware/__init__.py
pymodaq_plugins_nkt/hardware/superk_extreme.py
pymodaq_plugins_nkt/models/PIDModelTemplate.py
pymodaq_plugins_nkt/models/__init__.py
pymodaq_plugins_nkt/resources/VERSION
pymodaq_plugins_nkt/resources/__init__.py
pymodaq_plugins_nkt/resources/config_template.toml
pymodaq_plugins_nkt/scanners/__init__.py
pymodaq_plugins_nkt-1.0.0.dist-info/LICENSE
pymodaq_plugins_nkt-1.0.0.dist-info/METADATA
pymodaq_plugins_nkt-1.0.0.dist-info/WHEEL
pymodaq_plugins_nkt-1.0.0.dist-info/entry_points.txt
pymodaq_plugins_nkt-1.0.0.dist-info/top_level.txt
pymodaq_plugins_nkt-1.0.0.dist-info/RECORD
