Metadata-Version: 2.1
Name: pymodaq-plugins-nkt
Version: 1.0.0
Summary: A PyMoDAQ plugin for NKT Photonics instruments
Home-page: https://github.com/CRPP-META/pymodaq_plugins_nkt
Author: Bastien Bégon
Author-email: bastien.begon@crpp.cnrs.fr
License: MIT
Classifier: Programming Language :: Python :: 3
Classifier: Development Status :: 5 - Production/Stable
Classifier: Environment :: Other Environment
Classifier: Intended Audience :: Science/Research
Classifier: Topic :: Scientific/Engineering :: Human Machine Interfaces
Classifier: Topic :: Scientific/Engineering :: Visualization
Classifier: License :: OSI Approved :: MIT License
Classifier: Operating System :: OS Independent
Classifier: Topic :: Software Development :: Libraries :: Python Modules
Classifier: Topic :: Software Development :: User Interfaces
License-File: LICENSE
Requires-Dist: toml
Requires-Dist: pymodaq>=4.3.6
Requires-Dist: pylablib>=1.4.3
